ssdp_upnp/__init__.py
ssdp_upnp/ssdp.py
ssdp_upnp/util.py
ssdp_upnp-0.1.0.dist-info/LICENSE
ssdp_upnp-0.1.0.dist-info/METADATA
ssdp_upnp-0.1.0.dist-info/WHEEL
ssdp_upnp-0.1.0.dist-info/top_level.txt
ssdp_upnp-0.1.0.dist-info/RECORD
