Metadata-Version: 2.1
Name: ssdp-upnp
Version: 0.1.0
Summary: ssdp server and client of upnp
Home-page: https://github.com/tw7613781/ssdp_upnp
Author: tw7613781
Author-email: tw7613781@gmail.com
License: UNKNOWN
Platform: UNKNOWN
Classifier: Programming Language :: Python :: 3
Classifier: License :: OSI Approved :: MIT License
Classifier: Operating System :: OS Independent
Requires-Dist: colorlog (>=3.1.4)
Requires-Dist: miniupnpc (>=2.0.2)
